ryzomapi/__init__.py
ryzomapi-0.1.4.dist-info/DESCRIPTION.rst
ryzomapi-0.1.4.dist-info/METADATA
ryzomapi-0.1.4.dist-info/RECORD
ryzomapi-0.1.4.dist-info/WHEEL
ryzomapi-0.1.4.dist-info/metadata.json
ryzomapi-0.1.4.dist-info/top_level.txt
