Metadata-Version: 2.0
Name: ryzomapi
Version: 0.1.4
Summary: Unofficial python Ryzom API (removed)
Home-page: https://github.com/breard-r/py-ryzom-api
Author: Rodolphe Breard
Author-email: rodolphe@what.tf
License: UNKNOWN
Keywords: ryzom,api
Platform: UNKNOWN
Classifier: Development Status :: 7 - Inactive
